cp2k_input_tools/__init__.py
cp2k_input_tools/basissets/__init__.py
cp2k_input_tools/basissets/cp2k.py
cp2k_input_tools/basissets/crystal.py
cp2k_input_tools/cli/__init__.py
cp2k_input_tools/cli/cp2kgen.py
cp2k_input_tools/cli/cp2kget.py
cp2k_input_tools/cli/datafile_lint.py
cp2k_input_tools/cli/fromcp2k.py
cp2k_input_tools/cli/lint.py
cp2k_input_tools/cli/lsp.py
cp2k_input_tools/cli/tocp2k.py
cp2k_input_tools/cli/utils.py
cp2k_input_tools/cp2k_input.xml
cp2k_input_tools/generator.py
cp2k_input_tools/keyword_helpers.py
cp2k_input_tools/lineiterator.py
cp2k_input_tools/ls.py
cp2k_input_tools/parser.py
cp2k_input_tools/parser_errors.py
cp2k_input_tools/pint_units.txt
cp2k_input_tools/preprocessor.py
cp2k_input_tools/pseudopotentials/__init__.py
cp2k_input_tools/pseudopotentials/cp2k.py
cp2k_input_tools/pseudopotentials/ecp.py
cp2k_input_tools/templates/aiida_cp2k_calc.py.j2
cp2k_input_tools/tokenizer.py
cp2k_input_tools/utils.py
cp2k_input_tools-0.9.1.dist-info/LICENSE
cp2k_input_tools-0.9.1.dist-info/METADATA
cp2k_input_tools-0.9.1.dist-info/WHEEL
cp2k_input_tools-0.9.1.dist-info/entry_points.txt
cp2k_input_tools-0.9.1.dist-info/RECORD
