Metadata-Version: 2.1
Name: cp2k-input-tools
Version: 0.9.1
Summary: Python tools to handle CP2K input files
Home-page: https://github.com/cp2k/cp2k-input-tools
License: MIT
Author: Tiziano Müller
Author-email: tiziano.mueller@chem.uzh.ch
Requires-Python: >=3.9,<4
Classifier: Development Status :: 4 - Beta
Classifier: Environment :: Console
Classifier: Intended Audience :: Science/Research
Classifier: License :: OSI Approved :: MIT License
Classifier: Operating System :: OS Independent
Classifier: Programming Language :: Python :: 3
Classifier: Programming Language :: Python :: 3.9
Classifier: Programming Language :: Python :: 3.10
Classifier: Programming Language :: Python :: 3.11
Classifier: Programming Language :: Python :: 3.12
Classifier: Topic :: Scientific/Engineering :: Chemistry
Classifier: Topic :: Software Development :: Libraries :: Python Modules
Provides-Extra: lsp
Provides-Extra: yaml
Requires-Dist: Jinja2 (>=2.11.3,<4.0.0)
Requires-Dist: Pint (>=0.15,<0.24)
Requires-Dist: click (>=7.1.2,<9)
Requires-Dist: pydantic (>=2,<3.0)
Requires-Dist: pygls (>=1.0.0,<2.0.0) ; extra == "lsp"
Requires-Dist: ruamel.yaml (>=0.16.5,<0.19.0) ; extra == "yaml"
Requires-Dist: transitions (>=0.7,<0.10)
Project-URL: Repository, https://github.com/cp2k/cp2k-input-tools
